mymod/__init__.py
mymod/car.py
gbwyljp_simple_package-0.0.1.dist-info/LICENSE
gbwyljp_simple_package-0.0.1.dist-info/METADATA
gbwyljp_simple_package-0.0.1.dist-info/WHEEL
gbwyljp_simple_package-0.0.1.dist-info/top_level.txt
gbwyljp_simple_package-0.0.1.dist-info/RECORD
