Metadata-Version: 2.1
Name: gbwyljp-simple-package
Version: 0.0.1
Summary: A small example package, i make it for fun!
Home-page: https://github.com/Ljp66/package
Author: gbwyljp
Author-email: gbwyljp@gmail.com
Classifier: Programming Language :: Python :: 3
Classifier: License :: OSI Approved :: MIT License
Classifier: Operating System :: OS Independent
License-File: LICENSE
